loko_cli/__init__.py
loko_cli/apps/__init__.py
loko_cli/apps/cl.py
loko_cli/apps/loko_project_deploy.py
loko_cli/apps/loko_project_planning.py
loko_cli/apps/modify_a_container.py
loko_cli/apps/other.py
loko_cli/apps/prova_extensions.py
loko_cli/apps/prova_push.py
loko_cli/apps/provaceci.py
loko_cli/apps/provakubedepl.py
loko_cli/apps/provaorch.py
loko_cli/apps/total.py
loko_cli/apps/volumes.py
loko_cli/business/__init__.py
loko_cli/business/deployment/__init__.py
loko_cli/business/deployment/appliers/__init__.py
loko_cli/business/deployment/appliers/appliers.py
loko_cli/business/deployment/appliers/dcapplier2.py
loko_cli/business/deployment/appliers/docker_compose_applier.py
loko_cli/business/deployment/cloud/__init__.py
loko_cli/business/deployment/cloud/azure.py
loko_cli/business/deployment/cloud/ec2.py
loko_cli/business/deployment/planners/__init__.py
loko_cli/business/deployment/planners/docker_compose_planner.py
loko_cli/business/deployment/planners/planners.py
loko_cli/business/deployment/planners/provagendc.py
loko_cli/business/docker/__init__.py
loko_cli/business/docker/dockermanager.py
loko_cli/business/docker/log_collector.py
loko_cli/business/docker/utils.py
loko_cli/config/__init__.py
loko_cli/config/app_config.py
loko_cli/config/app_init.py
loko_cli/dao/__init__.py
loko_cli/dao/loko.py
loko_cli/examples/__init__.py
loko_cli/model/__init__.py
loko_cli/model/loko.py
loko_cli/model/microservices.py
loko_cli/model/plan.py
loko_cli/resources/__init__.py
loko_cli/resources/nginx/nginx-443.conf
loko_cli/resources/nginx/nginx.conf
loko_cli/services/__init__.py
loko_cli/services/services.py
loko_cli/test/__init__.py
loko_cli/utils/__init__.py
loko_cli/utils/jsonutils.py
loko_cli/utils/path_utils.py
loko_cli/utils/project_utils.py
loko_cli-0.0.5.dist-info/METADATA
loko_cli-0.0.5.dist-info/WHEEL
loko_cli-0.0.5.dist-info/entry_points.txt
loko_cli-0.0.5.dist-info/top_level.txt
loko_cli-0.0.5.dist-info/RECORD
