Metadata-Version: 2.1
Name: loko-cli
Version: 0.0.5
Author: Live Tech
Author-email: f.dantonio@ilivetech.it
Classifier: Programming Language :: Python :: 3
Classifier: License :: OSI Approved :: MIT License
Classifier: Operating System :: OS Independent
Requires-Python: >3.5.0
Requires-Dist: aiodocker
Requires-Dist: boto3
Requires-Dist: click
Requires-Dist: docker
Requires-Dist: kubernetes
Requires-Dist: loguru
Requires-Dist: loko-client
Requires-Dist: paramiko
Requires-Dist: ruamel.yaml
Requires-Dist: tenacity
Requires-Dist: azure-mgmt-resource
Requires-Dist: azure-mgmt-compute
Requires-Dist: azure-mgmt-network
Requires-Dist: azure-identity
